ferrmion-0.5.4.dist-info/METADATA
ferrmion-0.5.4.dist-info/WHEEL
ferrmion-0.5.4.dist-info/licenses/LICENSE
ferrmion/__init__.py
ferrmion/core.cpython-313-x86_64-linux-gnu.so
ferrmion/core.pyi
ferrmion/devices.py
ferrmion/encode/__init__.py
ferrmion/encode/base.py
ferrmion/encode/maxnto.py
ferrmion/encode/standard.py
ferrmion/encode/ternary_tree.py
ferrmion/encode/ternary_tree_node.py
ferrmion/hamiltonians.py
ferrmion/interop/__init__.py
ferrmion/interop/qiskit_mapper.py
ferrmion/optimize/__init__.py
ferrmion/optimize/bonsai.py
ferrmion/optimize/cost_functions.py
ferrmion/optimize/enumeration/__init__.py
ferrmion/optimize/enumeration/anneal.py
ferrmion/optimize/enumeration/evolutionary.py
ferrmion/optimize/hatt.py
ferrmion/optimize/huffman.py
ferrmion/optimize/rett.py
ferrmion/optimize/topphatt.py
ferrmion/py.typed
ferrmion/utils.py
ferrmion/visualise/__init__.py
ferrmion/visualise/graph.py
ferrmion/visualise/majorana.py
ferrmion-0.5.4.dist-info/RECORD
