Metadata-Version: 2.4
Name: ferrmion
Version: 0.5.4
Classifier: Programming Language :: Rust
Classifier: Programming Language :: Python :: Implementation :: CPython
Requires-Dist: deap>=1.4.3
Requires-Dist: rustworkx>=0.16.0
Requires-Dist: numpy>=2
Requires-Dist: matplotlib>=3.10.6 ; extra == 'viz'
Requires-Dist: qiskit>=2.2.1 ; extra == 'qiskit'
Requires-Dist: qiskit-nature>=0.7.2 ; extra == 'qiskit'
Provides-Extra: viz
Provides-Extra: qiskit
License-File: LICENSE
Requires-Python: >=3.12, <3.14
